{
    "arch": "x86_64",
    "build": "pl5321h7949ede_0",
    "build_number": 0,
    "channel": "conda-forge",
    "depends": [
        "ncurses",
        "__glibc >=2.17,<3.0.a0",
        "libgcc >=13",
        "ncurses >=6.5,<7.0a0"
    ],
    "extracted_package_dir": "/home/dmolodenskiy/AlphaPulldown/conda/pkgs/libedit-3.1.20240808-pl5321h7949ede_0",
    "files": [
        "include/editline/readline.h",
        "include/histedit.h",
        "lib/libedit.so",
        "lib/libedit.so.0",
        "lib/libedit.so.0.0.74",
        "lib/pkgconfig/libedit.pc",
        "share/man/man3/editline.3",
        "share/man/man3/el_deletestr.3",
        "share/man/man3/el_end.3",
        "share/man/man3/el_get.3",
        "share/man/man3/el_getc.3",
        "share/man/man3/el_gets.3",
        "share/man/man3/el_history.3",
        "share/man/man3/el_history_end.3",
        "share/man/man3/el_history_init.3",
        "share/man/man3/el_history_w.3",
        "share/man/man3/el_history_wend.3",
        "share/man/man3/el_history_winit.3",
        "share/man/man3/el_init.3",
        "share/man/man3/el_init_fd.3",
        "share/man/man3/el_insertstr.3",
        "share/man/man3/el_line.3",
        "share/man/man3/el_parse.3",
        "share/man/man3/el_push.3",
        "share/man/man3/el_reset.3",
        "share/man/man3/el_resize.3",
        "share/man/man3/el_set.3",
        "share/man/man3/el_source.3",
        "share/man/man3/el_tok_end.3",
        "share/man/man3/el_tok_init.3",
        "share/man/man3/el_tok_line.3",
        "share/man/man3/el_tok_reset.3",
        "share/man/man3/el_tok_str.3",
        "share/man/man3/el_tok_wend.3",
        "share/man/man3/el_tok_winit.3",
        "share/man/man3/el_tok_wline.3",
        "share/man/man3/el_tok_wreset.3",
        "share/man/man3/el_tok_wstr.3",
        "share/man/man3/el_wdeletestr.3",
        "share/man/man3/el_wget.3",
        "share/man/man3/el_wgetc.3",
        "share/man/man3/el_wgets.3",
        "share/man/man3/el_winsertstr.3",
        "share/man/man3/el_wline.3",
        "share/man/man3/el_wparse.3",
        "share/man/man3/el_wpush.3",
        "share/man/man3/el_wset.3",
        "share/man/man5/editrc.5",
        "share/man/man7/editline.7"
    ],
    "fn": "libedit-3.1.20240808-pl5321h7949ede_0.conda",
    "license": "BSD-2-Clause",
    "license_family": "BSD",
    "link": {
        "source": "/home/dmolodenskiy/AlphaPulldown/conda/pkgs/libedit-3.1.20240808-pl5321h7949ede_0",
        "type": 1
    },
    "md5": "8247f80f3dc464d9322e85007e307fe8",
    "name": "libedit",
    "package_tarball_full_path": "/home/dmolodenskiy/AlphaPulldown/conda/pkgs/libedit-3.1.20240808-pl5321h7949ede_0.tar.bz2",
    "paths_data": {
        "paths": [
            {
                "_path": "include/editline/readline.h",
                "path_type": "hardlink",
                "sha256": "c67b10c8cc3b478a64b7345dbf3261b8ba604d64dcbb619db685b77805535c45",
                "sha256_in_prefix": "c67b10c8cc3b478a64b7345dbf3261b8ba604d64dcbb619db685b77805535c45",
                "size_in_bytes": 9592
            },
            {
                "_path": "include/histedit.h",
                "path_type": "hardlink",
                "sha256": "352b99708fb81b1fb98f173d0e30a7286c4ee937e488bc75ad9e8e319e24f923",
                "sha256_in_prefix": "352b99708fb81b1fb98f173d0e30a7286c4ee937e488bc75ad9e8e319e24f923",
                "size_in_bytes": 9640
            },
            {
                "_path": "lib/libedit.so",
                "path_type": "softlink",
                "sha256_in_prefix": "d6be16a5061043b5eafaf29d18f9e46e8d25c7316bafa5eb81b7b232c938a1c1",
                "size_in_bytes": 17
            },
            {
                "_path": "lib/libedit.so.0",
                "path_type": "softlink",
                "sha256_in_prefix": "d6be16a5061043b5eafaf29d18f9e46e8d25c7316bafa5eb81b7b232c938a1c1",
                "size_in_bytes": 17
            },
            {
                "_path": "lib/libedit.so.0.0.74",
                "path_type": "hardlink",
                "sha256": "d6be16a5061043b5eafaf29d18f9e46e8d25c7316bafa5eb81b7b232c938a1c1",
                "sha256_in_prefix": "d6be16a5061043b5eafaf29d18f9e46e8d25c7316bafa5eb81b7b232c938a1c1",
                "size_in_bytes": 262096
            },
            {
                "_path": "lib/pkgconfig/libedit.pc",
                "path_type": "hardlink",
                "sha256": "b0b9de26320676ed6da0413d94a6e9e2774ce403316a0d53af38e892a6e00041",
                "sha256_in_prefix": "d5ae15fb380fd068778ebbc80a5eec955b47793a66a8e6c73a2aa6d6f225034b",
                "size_in_bytes": 587
            },
            {
                "_path": "share/man/man3/editline.3",
                "path_type": "hardlink",
                "sha256": "03c074075497b2aa3a20c229e76a6ba8f00dc70b38f1b323e7ab2cfbc8fa45d1",
                "sha256_in_prefix": "03c074075497b2aa3a20c229e76a6ba8f00dc70b38f1b323e7ab2cfbc8fa45d1",
                "size_in_bytes": 23827
            },
            {
                "_path": "share/man/man3/el_deletestr.3",
                "path_type": "softlink",
                "sha256_in_prefix": "03c074075497b2aa3a20c229e76a6ba8f00dc70b38f1b323e7ab2cfbc8fa45d1",
                "size_in_bytes": 10
            },
            {
                "_path": "share/man/man3/el_end.3",
                "path_type": "softlink",
                "sha256_in_prefix": "03c074075497b2aa3a20c229e76a6ba8f00dc70b38f1b323e7ab2cfbc8fa45d1",
                "size_in_bytes": 10
            },
            {
                "_path": "share/man/man3/el_get.3",
                "path_type": "softlink",
                "sha256_in_prefix": "03c074075497b2aa3a20c229e76a6ba8f00dc70b38f1b323e7ab2cfbc8fa45d1",
                "size_in_bytes": 10
            },
            {
                "_path": "share/man/man3/el_getc.3",
                "path_type": "softlink",
                "sha256_in_prefix": "03c074075497b2aa3a20c229e76a6ba8f00dc70b38f1b323e7ab2cfbc8fa45d1",
                "size_in_bytes": 10
            },
            {
                "_path": "share/man/man3/el_gets.3",
                "path_type": "softlink",
                "sha256_in_prefix": "03c074075497b2aa3a20c229e76a6ba8f00dc70b38f1b323e7ab2cfbc8fa45d1",
                "size_in_bytes": 10
            },
            {
                "_path": "share/man/man3/el_history.3",
                "path_type": "softlink",
                "sha256_in_prefix": "03c074075497b2aa3a20c229e76a6ba8f00dc70b38f1b323e7ab2cfbc8fa45d1",
                "size_in_bytes": 10
            },
            {
                "_path": "share/man/man3/el_history_end.3",
                "path_type": "softlink",
                "sha256_in_prefix": "03c074075497b2aa3a20c229e76a6ba8f00dc70b38f1b323e7ab2cfbc8fa45d1",
                "size_in_bytes": 10
            },
            {
                "_path": "share/man/man3/el_history_init.3",
                "path_type": "softlink",
                "sha256_in_prefix": "03c074075497b2aa3a20c229e76a6ba8f00dc70b38f1b323e7ab2cfbc8fa45d1",
                "size_in_bytes": 10
            },
            {
                "_path": "share/man/man3/el_history_w.3",
                "path_type": "softlink",
                "sha256_in_prefix": "03c074075497b2aa3a20c229e76a6ba8f00dc70b38f1b323e7ab2cfbc8fa45d1",
                "size_in_bytes": 10
            },
            {
                "_path": "share/man/man3/el_history_wend.3",
                "path_type": "softlink",
                "sha256_in_prefix": "03c074075497b2aa3a20c229e76a6ba8f00dc70b38f1b323e7ab2cfbc8fa45d1",
                "size_in_bytes": 10
            },
            {
                "_path": "share/man/man3/el_history_winit.3",
                "path_type": "softlink",
                "sha256_in_prefix": "03c074075497b2aa3a20c229e76a6ba8f00dc70b38f1b323e7ab2cfbc8fa45d1",
                "size_in_bytes": 10
            },
            {
                "_path": "share/man/man3/el_init.3",
                "path_type": "softlink",
                "sha256_in_prefix": "03c074075497b2aa3a20c229e76a6ba8f00dc70b38f1b323e7ab2cfbc8fa45d1",
                "size_in_bytes": 10
            },
            {
                "_path": "share/man/man3/el_init_fd.3",
                "path_type": "softlink",
                "sha256_in_prefix": "03c074075497b2aa3a20c229e76a6ba8f00dc70b38f1b323e7ab2cfbc8fa45d1",
                "size_in_bytes": 10
            },
            {
                "_path": "share/man/man3/el_insertstr.3",
                "path_type": "softlink",
                "sha256_in_prefix": "03c074075497b2aa3a20c229e76a6ba8f00dc70b38f1b323e7ab2cfbc8fa45d1",
                "size_in_bytes": 10
            },
            {
                "_path": "share/man/man3/el_line.3",
                "path_type": "softlink",
                "sha256_in_prefix": "03c074075497b2aa3a20c229e76a6ba8f00dc70b38f1b323e7ab2cfbc8fa45d1",
                "size_in_bytes": 10
            },
            {
                "_path": "share/man/man3/el_parse.3",
                "path_type": "softlink",
                "sha256_in_prefix": "03c074075497b2aa3a20c229e76a6ba8f00dc70b38f1b323e7ab2cfbc8fa45d1",
                "size_in_bytes": 10
            },
            {
                "_path": "share/man/man3/el_push.3",
                "path_type": "softlink",
                "sha256_in_prefix": "03c074075497b2aa3a20c229e76a6ba8f00dc70b38f1b323e7ab2cfbc8fa45d1",
                "size_in_bytes": 10
            },
            {
                "_path": "share/man/man3/el_reset.3",
                "path_type": "softlink",
                "sha256_in_prefix": "03c074075497b2aa3a20c229e76a6ba8f00dc70b38f1b323e7ab2cfbc8fa45d1",
                "size_in_bytes": 10
            },
            {
                "_path": "share/man/man3/el_resize.3",
                "path_type": "softlink",
                "sha256_in_prefix": "03c074075497b2aa3a20c229e76a6ba8f00dc70b38f1b323e7ab2cfbc8fa45d1",
                "size_in_bytes": 10
            },
            {
                "_path": "share/man/man3/el_set.3",
                "path_type": "softlink",
                "sha256_in_prefix": "03c074075497b2aa3a20c229e76a6ba8f00dc70b38f1b323e7ab2cfbc8fa45d1",
                "size_in_bytes": 10
            },
            {
                "_path": "share/man/man3/el_source.3",
                "path_type": "softlink",
                "sha256_in_prefix": "03c074075497b2aa3a20c229e76a6ba8f00dc70b38f1b323e7ab2cfbc8fa45d1",
                "size_in_bytes": 10
            },
            {
                "_path": "share/man/man3/el_tok_end.3",
                "path_type": "softlink",
                "sha256_in_prefix": "03c074075497b2aa3a20c229e76a6ba8f00dc70b38f1b323e7ab2cfbc8fa45d1",
                "size_in_bytes": 10
            },
            {
                "_path": "share/man/man3/el_tok_init.3",
                "path_type": "softlink",
                "sha256_in_prefix": "03c074075497b2aa3a20c229e76a6ba8f00dc70b38f1b323e7ab2cfbc8fa45d1",
                "size_in_bytes": 10
            },
            {
                "_path": "share/man/man3/el_tok_line.3",
                "path_type": "softlink",
                "sha256_in_prefix": "03c074075497b2aa3a20c229e76a6ba8f00dc70b38f1b323e7ab2cfbc8fa45d1",
                "size_in_bytes": 10
            },
            {
                "_path": "share/man/man3/el_tok_reset.3",
                "path_type": "softlink",
                "sha256_in_prefix": "03c074075497b2aa3a20c229e76a6ba8f00dc70b38f1b323e7ab2cfbc8fa45d1",
                "size_in_bytes": 10
            },
            {
                "_path": "share/man/man3/el_tok_str.3",
                "path_type": "softlink",
                "sha256_in_prefix": "03c074075497b2aa3a20c229e76a6ba8f00dc70b38f1b323e7ab2cfbc8fa45d1",
                "size_in_bytes": 10
            },
            {
                "_path": "share/man/man3/el_tok_wend.3",
                "path_type": "softlink",
                "sha256_in_prefix": "03c074075497b2aa3a20c229e76a6ba8f00dc70b38f1b323e7ab2cfbc8fa45d1",
                "size_in_bytes": 10
            },
            {
                "_path": "share/man/man3/el_tok_winit.3",
                "path_type": "softlink",
                "sha256_in_prefix": "03c074075497b2aa3a20c229e76a6ba8f00dc70b38f1b323e7ab2cfbc8fa45d1",
                "size_in_bytes": 10
            },
            {
                "_path": "share/man/man3/el_tok_wline.3",
                "path_type": "softlink",
                "sha256_in_prefix": "03c074075497b2aa3a20c229e76a6ba8f00dc70b38f1b323e7ab2cfbc8fa45d1",
                "size_in_bytes": 10
            },
            {
                "_path": "share/man/man3/el_tok_wreset.3",
                "path_type": "softlink",
                "sha256_in_prefix": "03c074075497b2aa3a20c229e76a6ba8f00dc70b38f1b323e7ab2cfbc8fa45d1",
                "size_in_bytes": 10
            },
            {
                "_path": "share/man/man3/el_tok_wstr.3",
                "path_type": "softlink",
                "sha256_in_prefix": "03c074075497b2aa3a20c229e76a6ba8f00dc70b38f1b323e7ab2cfbc8fa45d1",
                "size_in_bytes": 10
            },
            {
                "_path": "share/man/man3/el_wdeletestr.3",
                "path_type": "softlink",
                "sha256_in_prefix": "03c074075497b2aa3a20c229e76a6ba8f00dc70b38f1b323e7ab2cfbc8fa45d1",
                "size_in_bytes": 10
            },
            {
                "_path": "share/man/man3/el_wget.3",
                "path_type": "softlink",
                "sha256_in_prefix": "03c074075497b2aa3a20c229e76a6ba8f00dc70b38f1b323e7ab2cfbc8fa45d1",
                "size_in_bytes": 10
            },
            {
                "_path": "share/man/man3/el_wgetc.3",
                "path_type": "softlink",
                "sha256_in_prefix": "03c074075497b2aa3a20c229e76a6ba8f00dc70b38f1b323e7ab2cfbc8fa45d1",
                "size_in_bytes": 10
            },
            {
                "_path": "share/man/man3/el_wgets.3",
                "path_type": "softlink",
                "sha256_in_prefix": "03c074075497b2aa3a20c229e76a6ba8f00dc70b38f1b323e7ab2cfbc8fa45d1",
                "size_in_bytes": 10
            },
            {
                "_path": "share/man/man3/el_winsertstr.3",
                "path_type": "softlink",
                "sha256_in_prefix": "03c074075497b2aa3a20c229e76a6ba8f00dc70b38f1b323e7ab2cfbc8fa45d1",
                "size_in_bytes": 10
            },
            {
                "_path": "share/man/man3/el_wline.3",
                "path_type": "softlink",
                "sha256_in_prefix": "03c074075497b2aa3a20c229e76a6ba8f00dc70b38f1b323e7ab2cfbc8fa45d1",
                "size_in_bytes": 10
            },
            {
                "_path": "share/man/man3/el_wparse.3",
                "path_type": "softlink",
                "sha256_in_prefix": "03c074075497b2aa3a20c229e76a6ba8f00dc70b38f1b323e7ab2cfbc8fa45d1",
                "size_in_bytes": 10
            },
            {
                "_path": "share/man/man3/el_wpush.3",
                "path_type": "softlink",
                "sha256_in_prefix": "03c074075497b2aa3a20c229e76a6ba8f00dc70b38f1b323e7ab2cfbc8fa45d1",
                "size_in_bytes": 10
            },
            {
                "_path": "share/man/man3/el_wset.3",
                "path_type": "softlink",
                "sha256_in_prefix": "03c074075497b2aa3a20c229e76a6ba8f00dc70b38f1b323e7ab2cfbc8fa45d1",
                "size_in_bytes": 10
            },
            {
                "_path": "share/man/man5/editrc.5",
                "path_type": "hardlink",
                "sha256": "6ccf6a545e09863fbe659ee742bcafabc212359295b9f3f6abc45ea5eea2da86",
                "sha256_in_prefix": "6ccf6a545e09863fbe659ee742bcafabc212359295b9f3f6abc45ea5eea2da86",
                "size_in_bytes": 3598
            },
            {
                "_path": "share/man/man7/editline.7",
                "path_type": "hardlink",
                "sha256": "0bcb8718502ff3eea01f458a0b819de4ca3bb1ef015d417f48d3961e15cd06f1",
                "sha256_in_prefix": "0bcb8718502ff3eea01f458a0b819de4ca3bb1ef015d417f48d3961e15cd06f1",
                "size_in_bytes": 33136
            }
        ],
        "paths_version": 1
    },
    "platform": "linux",
    "requested_spec": "conda-forge/linux-64::libedit==3.1.20240808=pl5321h7949ede_0[md5=8247f80f3dc464d9322e85007e307fe8]",
    "sha256": "4d0d69ddf9cc7d724a1ccf3a9852e44c8aea9825692582bac2c4e8d21ec95ccd",
    "size": 134657,
    "subdir": "linux-64",
    "timestamp": 1736191912705,
    "url": "https://conda.anaconda.org/conda-forge/linux-64/libedit-3.1.20240808-pl5321h7949ede_0.conda",
    "version": "3.1.20240808"
}